{"train_algo/loss_group:0": NaN, "train_algo/loss_group:1": NaN, "train_algo/loss_group:2": NaN, "train_algo/loss_group:3": 0.040593087673187256, "train_algo/loss_group:4": 0.04741143435239792, "train_algo/loss_avg": 0.04400226101279259, "train_algo/acc_group:0": NaN, "train_algo/acc_group:1": NaN, "train_algo/acc_group:2": NaN, "train_algo/acc_group:3": 1.0, "train_algo/acc_group:4": 1.0, "train_algo/acc_avg": 1.0, "train_algo/objective": 0.030585529282689095, "train_algo/penalty": 0.03974228352308273, "train_algo/weight_group:0": NaN, "train_algo/weight_group:1": NaN, "train_algo/weight_group:2": NaN, "train_algo/weight_group:3": 0.4175773859024048, "train_algo/weight_group:4": 0.2037597894668579, "train_algo/count_group:0": 0.0, "train_algo/count_group:1": 0.0, "train_algo/count_group:2": 0.0, "train_algo/count_group:3": 16.0, "train_algo/count_group:4": 16.0, "train_algo/count": 32, "train_algo/epoch": 4, "train_algo/batch": 9451, "_runtime": 15381, "_timestamp": 1615806739, "_step": 964, "train_eval/acc_avg": 0.9711406230926514, "train_eval/acc_slide:0": 0.9811137318611145, "train_eval/count_slide:0": 7201.0, "train_eval/acc_slide:1": 0.9777894020080566, "train_eval/count_slide:1": 7654.0, "train_eval/acc_slide:2": 0.9300467371940613, "train_eval/count_slide:2": 6633.0, "train_eval/acc_slide:3": 0.9834160804748535, "train_eval/count_slide:3": 23155.0, "train_eval/acc_slide:4": 0.9821215867996216, "train_eval/count_slide:4": 12585.0, "train_eval/acc_slide:5": 0.9299065470695496, "train_eval/count_slide:5": 5564.0, "train_eval/acc_slide:6": 0.9758419990539551, "train_eval/count_slide:6": 5671.0, "train_eval/acc_slide:7": 0.9754716753959656, "train_eval/count_slide:7": 2650.0, "train_eval/acc_slide:8": 0.9776461720466614, "train_eval/count_slide:8": 23128.0, "train_eval/acc_slide:9": 0.9222978353500366, "train_eval/count_slide:9": 6319.0, "train_eval/acc_slide:10": 0.0, "train_eval/count_slide:10": 0.0, "train_eval/acc_slide:11": 0.0, "train_eval/count_slide:11": 0.0, "train_eval/acc_slide:12": 0.0, "train_eval/count_slide:12": 0.0, "train_eval/acc_slide:13": 0.0, "train_eval/count_slide:13": 0.0, "train_eval/acc_slide:14": 0.0, "train_eval/count_slide:14": 0.0, "train_eval/acc_slide:15": 0.0, "train_eval/count_slide:15": 0.0, "train_eval/acc_slide:16": 0.0, "train_eval/count_slide:16": 0.0, "train_eval/acc_slide:17": 0.0, "train_eval/count_slide:17": 0.0, "train_eval/acc_slide:18": 0.0, "train_eval/count_slide:18": 0.0, "train_eval/acc_slide:19": 0.0, "train_eval/count_slide:19": 0.0, "train_eval/acc_slide:20": 0.0, "train_eval/count_slide:20": 0.0, "train_eval/acc_slide:21": 0.0, "train_eval/count_slide:21": 0.0, "train_eval/acc_slide:22": 0.0, "train_eval/count_slide:22": 0.0, "train_eval/acc_slide:23": 0.0, "train_eval/count_slide:23": 0.0, "train_eval/acc_slide:24": 0.0, "train_eval/count_slide:24": 0.0, "train_eval/acc_slide:25": 0.0, "train_eval/count_slide:25": 0.0, "train_eval/acc_slide:26": 0.0, "train_eval/count_slide:26": 0.0, "train_eval/acc_slide:27": 0.0, "train_eval/count_slide:27": 0.0, "train_eval/acc_slide:28": 0.0, "train_eval/count_slide:28": 0.0, "train_eval/acc_slide:29": 0.0, "train_eval/count_slide:29": 0.0, "train_eval/acc_slide:30": 0.9847564697265625, "train_eval/count_slide:30": 8069.0, "train_eval/acc_slide:31": 0.9856564998626709, "train_eval/count_slide:31": 2719.0, "train_eval/acc_slide:32": 0.9688875675201416, "train_eval/count_slide:32": 6814.0, "train_eval/acc_slide:33": 0.9830827116966248, "train_eval/count_slide:33": 3192.0, "train_eval/acc_slide:34": 0.9567983746528625, "train_eval/count_slide:34": 2986.0, "train_eval/acc_slide:35": 0.958053708076477, "train_eval/count_slide:35": 4768.0, "train_eval/acc_slide:36": 0.990602433681488, "train_eval/count_slide:36": 8300.0, "train_eval/acc_slide:37": 0.981717586517334, "train_eval/count_slide:37": 4157.0, "train_eval/acc_slide:38": 0.9638960361480713, "train_eval/count_slide:38": 44815.0, "train_eval/acc_slide:39": 0.9697973728179932, "train_eval/count_slide:39": 15396.0, "train_eval/acc_slide:40": 0.9824384450912476, "train_eval/count_slide:40": 4954.0, "train_eval/acc_slide:41": 0.9896060824394226, "train_eval/count_slide:41": 7793.0, "train_eval/acc_slide:42": 0.9778070449829102, "train_eval/count_slide:42": 5317.0, "train_eval/acc_slide:43": 0.9756938219070435, "train_eval/count_slide:43": 5513.0, "train_eval/acc_slide:44": 0.9825359582901001, "train_eval/count_slide:44": 5497.0, "train_eval/acc_slide:45": 0.9746915102005005, "train_eval/count_slide:45": 4781.0, "train_eval/acc_slide:46": 0.9746041297912598, "train_eval/count_slide:46": 3347.0, "train_eval/acc_slide:47": 0.977168083190918, "train_eval/count_slide:47": 10205.0, "train_eval/acc_slide:48": 0.9686904549598694, "train_eval/count_slide:48": 41968.0, "train_eval/acc_slide:49": 0.9569187164306641, "train_eval/count_slide:49": 11281.0, "train_eval/acc_wg": 0.9222978353500366, "train_eval/epoch": 4, "val_algo/loss_group:0": NaN, "val_algo/loss_group:1": 0.426577627658844, "val_algo/loss_group:2": NaN, "val_algo/loss_group:3": NaN, "val_algo/loss_group:4": NaN, "val_algo/loss_avg": 0.42657783339425454, "val_algo/acc_group:0": NaN, "val_algo/acc_group:1": 0.8135172724723816, "val_algo/acc_group:2": NaN, "val_algo/acc_group:3": NaN, "val_algo/acc_group:4": NaN, "val_algo/acc_avg": 0.8135170754341524, "val_algo/objective": 0.0, "val_algo/penalty": 0.0, "val_algo/weight_group:0": NaN, "val_algo/weight_group:1": 0.0, "val_algo/weight_group:2": NaN, "val_algo/weight_group:3": NaN, "val_algo/weight_group:4": NaN, "val_algo/count_group:0": 0.0, "val_algo/count_group:1": 34904.0, "val_algo/count_group:2": 0.0, "val_algo/count_group:3": 0.0, "val_algo/count_group:4": 0.0, "val_algo/count": 34904, "val_algo/epoch": 4, "val_algo/batch": 1091, "val_eval/acc_avg": 0.8135170936584473, "val_eval/acc_slide:0": 0.0, "val_eval/count_slide:0": 0.0, "val_eval/acc_slide:1": 0.0, "val_eval/count_slide:1": 0.0, "val_eval/acc_slide:2": 0.0, "val_eval/count_slide:2": 0.0, "val_eval/acc_slide:3": 0.0, "val_eval/count_slide:3": 0.0, "val_eval/acc_slide:4": 0.0, "val_eval/count_slide:4": 0.0, "val_eval/acc_slide:5": 0.0, "val_eval/count_slide:5": 0.0, "val_eval/acc_slide:6": 0.0, "val_eval/count_slide:6": 0.0, "val_eval/acc_slide:7": 0.0, "val_eval/count_slide:7": 0.0, "val_eval/acc_slide:8": 0.0, "val_eval/count_slide:8": 0.0, "val_eval/acc_slide:9": 0.0, "val_eval/count_slide:9": 0.0, "val_eval/acc_slide:10": 0.4860442876815796, "val_eval/count_slide:10": 2078.0, "val_eval/acc_slide:11": 0.66356360912323, "val_eval/count_slide:11": 5371.0, "val_eval/acc_slide:12": 0.8463343381881714, "val_eval/count_slide:12": 1705.0, "val_eval/acc_slide:13": 0.9377162456512451, "val_eval/count_slide:13": 10404.0, "val_eval/acc_slide:14": 0.837837815284729, "val_eval/count_slide:14": 888.0, "val_eval/acc_slide:15": 0.8975050449371338, "val_eval/count_slide:15": 2966.0, "val_eval/acc_slide:16": 0.8980084657669067, "val_eval/count_slide:16": 4971.0, "val_eval/acc_slide:17": 0.71380215883255, "val_eval/count_slide:17": 2659.0, "val_eval/acc_slide:18": 0.7945098280906677, "val_eval/count_slide:18": 1275.0, "val_eval/acc_slide:19": 0.7116351127624512, "val_eval/count_slide:19": 2587.0, "val_eval/acc_slide:20": 0.0, "val_eval/count_slide:20": 0.0, "val_eval/acc_slide:21": 0.0, "val_eval/count_slide:21": 0.0, "val_eval/acc_slide:22": 0.0, "val_eval/count_slide:22": 0.0, "val_eval/acc_slide:23": 0.0, "val_eval/count_slide:23": 0.0, "val_eval/acc_slide:24": 0.0, "val_eval/count_slide:24": 0.0, "val_eval/acc_slide:25": 0.0, "val_eval/count_slide:25": 0.0, "val_eval/acc_slide:26": 0.0, "val_eval/count_slide:26": 0.0, "val_eval/acc_slide:27": 0.0, "val_eval/count_slide:27": 0.0, "val_eval/acc_slide:28": 0.0, "val_eval/count_slide:28": 0.0, "val_eval/acc_slide:29": 0.0, "val_eval/count_slide:29": 0.0, "val_eval/acc_slide:30": 0.0, "val_eval/count_slide:30": 0.0, "val_eval/acc_slide:31": 0.0, "val_eval/count_slide:31": 0.0, "val_eval/acc_slide:32": 0.0, "val_eval/count_slide:32": 0.0, "val_eval/acc_slide:33": 0.0, "val_eval/count_slide:33": 0.0, "val_eval/acc_slide:34": 0.0, "val_eval/count_slide:34": 0.0, "val_eval/acc_slide:35": 0.0, "val_eval/count_slide:35": 0.0, "val_eval/acc_slide:36": 0.0, "val_eval/count_slide:36": 0.0, "val_eval/acc_slide:37": 0.0, "val_eval/count_slide:37": 0.0, "val_eval/acc_slide:38": 0.0, "val_eval/count_slide:38": 0.0, "val_eval/acc_slide:39": 0.0, "val_eval/count_slide:39": 0.0, "val_eval/acc_slide:40": 0.0, "val_eval/count_slide:40": 0.0, "val_eval/acc_slide:41": 0.0, "val_eval/count_slide:41": 0.0, "val_eval/acc_slide:42": 0.0, "val_eval/count_slide:42": 0.0, "val_eval/acc_slide:43": 0.0, "val_eval/count_slide:43": 0.0, "val_eval/acc_slide:44": 0.0, "val_eval/count_slide:44": 0.0, "val_eval/acc_slide:45": 0.0, "val_eval/count_slide:45": 0.0, "val_eval/acc_slide:46": 0.0, "val_eval/count_slide:46": 0.0, "val_eval/acc_slide:47": 0.0, "val_eval/count_slide:47": 0.0, "val_eval/acc_slide:48": 0.0, "val_eval/count_slide:48": 0.0, "val_eval/acc_slide:49": 0.0, "val_eval/count_slide:49": 0.0, "val_eval/acc_wg": 0.4860442876815796, "val_eval/epoch": 4}